{
    "frame_flag": "",
    "frame_index": 261,
    "header": "Astyx Version_01_00",
    "objects": [
        {
            "center3d": [
                55.37886849915492,
                23.318991074109526,
                -0.4132742608825122
            ],
            "classname": "Car",
            "created_by": "g.kuschk",
            "dimension3d": [
                4.0,
                1.8,
                1.576814785229763
            ],
            "label_certainty": 0,
            "measured_by": {
                "Camera": 1,
                "Lidar": 1,
                "Radar": 1
            },
            "object_id": -1,
            "occlusion": 0,
            "orientation_quat": [
                0.8500805995376359,
                -0.03664925933229765,
                0.0018773819511400736,
                0.5253725169031371
            ],
            "score": -1.0
        },
        {
            "center3d": [
                37.51,
                -9.06,
                1.79
            ],
            "classname": "Car",
            "created_by": "g.kuschk",
            "dimension3d": [
                5.13,
                1.83,
                2.07
            ],
            "label_certainty": 0,
            "measured_by": {
                "Camera": 1,
                "Lidar": 1,
                "Radar": 1
            },
            "object_id": -1,
            "occlusion": 0,
            "orientation_quat": [
                0.8615687199063309,
                -0.04025819127194261,
                0.007141418117762778,
                0.5059917183726876
            ],
            "score": -1.0
        },
        {
            "center3d": [
                7.951954461197539,
                -4.725911959509831,
                -0.25640893070123283
            ],
            "classname": "Car",
            "created_by": "g.kuschk",
            "dimension3d": [
                3.3690440163507396,
                1.8,
                1.5
            ],
            "label_certainty": 0,
            "measured_by": {
                "Camera": 1,
                "Lidar": 1,
                "Radar": 1
            },
            "object_id": -1,
            "occlusion": 0,
            "orientation_quat": [
                0.9480849657669154,
                -0.024933989329462145,
                -0.026927427164627128,
                -0.3158925569385246
            ],
            "score": -1.0
        }
    ]
}